[{"startTime":"2022-02-09T21:00:00-05:00","endTime":"2022-02-10T06:00:00-05:00","isDaytime":false,"temperature":31,"temperatureUnit":"F","temperatureTrend":null,"windSpeed":"5 mph","windDirection":"S","icon":"https://api.weather.gov/icons/land/night/sct?size=medium","shortForecast":"Partly Cloudy","detailedForecast":"Partly cloudy, with a low around 31. South wind around 5 mph.","updated":"2022-02-10T02:18:45+00:00"},{"startTime":"2022-02-10T06:00:00-05:00","endTime":"2022-02-10T18:00:00-05:00","isDaytime":true,"temperature":49,"temperatureUnit":"F","temperatureTrend":"falling","windSpeed":"5 to 10 mph","windDirection":"SW","icon":"https://api.weather.gov/icons/land/day/sct?size=medium","shortForecast":"Mostly Sunny","detailedForecast":"Mostly sunny. High near 49, with temperatures falling to around 42 in the afternoon. Southwest wind 5 to 10 mph, with gusts as high as 21 mph.","updated":"2022-02-10T02:18:45+00:00"},{"startTime":"2022-02-10T18:00:00-05:00","endTime":"2022-02-11T06:00:00-05:00","isDaytime":false,"temperature":31,"temperatureUnit":"F","temperatureTrend":null,"windSpeed":"7 mph","windDirection":"W","icon":"https://api.weather.gov/icons/land/night/few?size=medium","shortForecast":"Mostly Clear","detailedForecast":"Mostly clear, with a low around 31. West wind around 7 mph.","updated":"2022-02-10T02:18:45+00:00"},{"startTime":"2022-02-11T06:00:00-05:00","endTime":"2022-02-11T18:00:00-05:00","isDaytime":true,"temperature":46,"temperatureUnit":"F","temperatureTrend":null,"windSpeed":"5 to 10 mph","windDirection":"SW","icon":"https://api.weather.gov/icons/land/day/few?size=medium","shortForecast":"Sunny","detailedForecast":"Sunny, with a high near 46. Southwest wind 5 to 10 mph.","updated":"2022-02-10T02:18:45+00:00"},{"startTime":"2022-02-11T18:00:00-05:00","endTime":"2022-02-12T06:00:00-05:00","isDaytime":false,"temperature":38,"temperatureUnit":"F","temperatureTrend":null,"windSpeed":"10 mph","windDirection":"SW","icon":"https://api.weather.gov/icons/land/night/bkn?size=medium","shortForecast":"Mostly Cloudy","detailedForecast":"Mostly cloudy, with a low around 38. Southwest wind around 10 mph.","updated":"2022-02-10T02:18:45+00:00"},{"startTime":"2022-02-12T06:00:00-05:00","endTime":"2022-02-12T18:00:00-05:00","isDaytime":true,"temperature":53,"temperatureUnit":"F","temperatureTrend":null,"windSpeed":"8 to 12 mph","windDirection":"SW","icon":"https://api.weather.gov/icons/land/day/bkn?size=medium","shortForecast":"Partly Sunny","detailedForecast":"Partly sunny, with a high near 53. Southwest wind 8 to 12 mph.","updated":"2022-02-10T02:18:45+00:00"},{"startTime":"2022-02-12T18:00:00-05:00","endTime":"2022-02-13T06:00:00-05:00","isDaytime":false,"temperature":25,"temperatureUnit":"F","temperatureTrend":null,"windSpeed":"8 mph","windDirection":"NW","icon":"https://api.weather.gov/icons/land/night/bkn/snow,30?size=medium","shortForecast":"Mostly Cloudy then Chance Light Snow","detailedForecast":"A chance of snow after midnight. Mostly cloudy, with a low around 25. Northwest wind around 8 mph. Chance of precipitation is 30%.","updated":"2022-02-10T02:18:45+00:00"},{"startTime":"2022-02-13T06:00:00-05:00","endTime":"2022-02-13T18:00:00-05:00","isDaytime":true,"temperature":29,"temperatureUnit":"F","temperatureTrend":null,"windSpeed":"6 to 9 mph","windDirection":"N","icon":"https://api.weather.gov/icons/land/day/snow,50?size=medium","shortForecast":"Chance Light Snow","detailedForecast":"A chance of snow. Mostly cloudy, with a high near 29. North wind 6 to 9 mph. Chance of precipitation is 50%.","updated":"2022-02-10T02:18:45+00:00"},{"startTime":"2022-02-13T18:00:00-05:00","endTime":"2022-02-14T06:00:00-05:00","isDaytime":false,"temperature":14,"temperatureUnit":"F","temperatureTrend":null,"windSpeed":"9 mph","windDirection":"N","icon":"https://api.weather.gov/icons/land/night/snow,40/snow,30?size=medium","shortForecast":"Chance Light Snow","detailedForecast":"A chance of snow. Mostly cloudy, with a low around 14. North wind around 9 mph. Chance of precipitation is 40%.","updated":"2022-02-10T02:18:45+00:00"},{"startTime":"2022-02-14T06:00:00-05:00","endTime":"2022-02-14T18:00:00-05:00","isDaytime":true,"temperature":24,"temperatureUnit":"F","temperatureTrend":null,"windSpeed":"9 mph","windDirection":"NW","icon":"https://api.weather.gov/icons/land/day/sct?size=medium","shortForecast":"Mostly Sunny","detailedForecast":"Mostly sunny, with a high near 24. Northwest wind around 9 mph.","updated":"2022-02-10T02:18:45+00:00"},{"startTime":"2022-02-14T18:00:00-05:00","endTime":"2022-02-15T06:00:00-05:00","isDaytime":false,"temperature":11,"temperatureUnit":"F","temperatureTrend":null,"windSpeed":"6 mph","windDirection":"NW","icon":"https://api.weather.gov/icons/land/night/sct?size=medium","shortForecast":"Partly Cloudy","detailedForecast":"Partly cloudy, with a low around 11. Northwest wind around 6 mph.","updated":"2022-02-10T02:18:45+00:00"},{"startTime":"2022-02-15T06:00:00-05:00","endTime":"2022-02-15T18:00:00-05:00","isDaytime":true,"temperature":29,"temperatureUnit":"F","temperatureTrend":null,"windSpeed":"6 to 9 mph","windDirection":"NW","icon":"https://api.weather.gov/icons/land/day/few?size=medium","shortForecast":"Sunny","detailedForecast":"Sunny, with a high near 29. Northwest wind 6 to 9 mph.","updated":"2022-02-10T02:18:45+00:00"},{"startTime":"2022-02-15T18:00:00-05:00","endTime":"2022-02-16T06:00:00-05:00","isDaytime":false,"temperature":17,"temperatureUnit":"F","temperatureTrend":null,"windSpeed":"6 mph","windDirection":"W","icon":"https://api.weather.gov/icons/land/night/sct?size=medium","shortForecast":"Partly Cloudy","detailedForecast":"Partly cloudy, with a low around 17. West wind around 6 mph.","updated":"2022-02-10T02:18:45+00:00"},{"startTime":"2022-02-16T06:00:00-05:00","endTime":"2022-02-16T18:00:00-05:00","isDaytime":true,"temperature":42,"temperatureUnit":"F","temperatureTrend":null,"windSpeed":"6 to 14 mph","windDirection":"SW","icon":"https://api.weather.gov/icons/land/day/bkn?size=medium","shortForecast":"Partly Sunny","detailedForecast":"Partly sunny, with a high near 42. Southwest wind 6 to 14 mph.","updated":"2022-02-10T02:18:45+00:00"}]