{
    "@context": [
        "https://geojson.org/geojson-ld/geojson-context.jsonld",
        {
            "@version": "1.1",
            "wx": "https://api.weather.gov/ontology#",
            "geo": "http://www.opengis.net/ont/geosparql#",
            "unit": "http://codes.wmo.int/common/unit/",
            "@vocab": "https://api.weather.gov/ontology#"
        }
    ],
    "type": "Feature",
    "geometry": {
        "type": "Polygon",
        "coordinates": [
            [
                [
                    -71.158981900000001,
                    42.428830900000001
                ],
                [
                    -71.164132499999994,
                    42.407429499999999
                ],
                [
                    -71.135151099999987,
                    42.403625599999998
                ],
                [
                    -71.129994499999981,
                    42.425026599999995
                ],
                [
                    -71.158981900000001,
                    42.428830900000001
                ]
            ]
        ]
    },
    "properties": {
        "updated": "2021-11-17T03:03:18+00:00",
        "units": "us",
        "forecastGenerator": "BaselineForecastGenerator",
        "generatedAt": "2021-11-17T04:30:42+00:00",
        "updateTime": "2021-11-17T03:03:18+00:00",
        "validTimes": "2021-11-16T21:00:00+00:00/P8DT6H",
        "elevation": {
            "unitCode": "wmoUnit:m",
            "value": 10.058400000000001
        },
        "periods": [
            {
                "number": 1,
                "name": "Tonight",
                "startTime": "2021-11-16T23:00:00-05:00",
                "endTime": "2021-11-17T06:00:00-05:00",
                "isDaytime": false,
                "temperature": 30,
                "temperatureUnit": "F",
                "temperatureTrend": null,
                "windSpeed": "7 mph",
                "windDirection": "W",
                "icon": "https://api.weather.gov/icons/land/night/few?size=medium",
                "shortForecast": "Mostly Clear",
                "detailedForecast": "Mostly clear, with a low around 30. West wind around 7 mph."
            },
            {
                "number": 2,
                "name": "Wednesday",
                "startTime": "2021-11-17T06:00:00-05:00",
                "endTime": "2021-11-17T18:00:00-05:00",
                "isDaytime": true,
                "temperature": 51,
                "temperatureUnit": "F",
                "temperatureTrend": "falling",
                "windSpeed": "3 to 7 mph",
                "windDirection": "SW",
                "icon": "https://api.weather.gov/icons/land/day/sct?size=medium",
                "shortForecast": "Mostly Sunny",
                "detailedForecast": "Mostly sunny. High near 51, with temperatures falling to around 45 in the afternoon. Southwest wind 3 to 7 mph."
            },
            {
                "number": 3,
                "name": "Wednesday Night",
                "startTime": "2021-11-17T18:00:00-05:00",
                "endTime": "2021-11-18T06:00:00-05:00",
                "isDaytime": false,
                "temperature": 44,
                "temperatureUnit": "F",
                "temperatureTrend": "rising",
                "windSpeed": "9 mph",
                "windDirection": "S",
                "icon": "https://api.weather.gov/icons/land/night/bkn?size=medium",
                "shortForecast": "Mostly Cloudy",
                "detailedForecast": "Mostly cloudy. Low around 44, with temperatures rising to around 50 overnight. South wind around 9 mph."
            },
            {
                "number": 4,
                "name": "Thursday",
                "startTime": "2021-11-18T06:00:00-05:00",
                "endTime": "2021-11-18T18:00:00-05:00",
                "isDaytime": true,
                "temperature": 68,
                "temperatureUnit": "F",
                "temperatureTrend": null,
                "windSpeed": "8 to 14 mph",
                "windDirection": "SW",
                "icon": "https://api.weather.gov/icons/land/day/sct?size=medium",
                "shortForecast": "Mostly Sunny",
                "detailedForecast": "Mostly sunny, with a high near 68. Southwest wind 8 to 14 mph."
            },
            {
                "number": 5,
                "name": "Thursday Night",
                "startTime": "2021-11-18T18:00:00-05:00",
                "endTime": "2021-11-19T06:00:00-05:00",
                "isDaytime": false,
                "temperature": 38,
                "temperatureUnit": "F",
                "temperatureTrend": null,
                "windSpeed": "10 mph",
                "windDirection": "W",
                "icon": "https://api.weather.gov/icons/land/night/rain,50/rain,80?size=medium",
                "shortForecast": "Light Rain",
                "detailedForecast": "A chance of rain showers between 8pm and 11pm, then rain. Mostly cloudy, with a low around 38. West wind around 10 mph. Chance of precipitation is 80%."
            },
            {
                "number": 6,
                "name": "Friday",
                "startTime": "2021-11-19T06:00:00-05:00",
                "endTime": "2021-11-19T18:00:00-05:00",
                "isDaytime": true,
                "temperature": 48,
                "temperatureUnit": "F",
                "temperatureTrend": null,
                "windSpeed": "9 to 15 mph",
                "windDirection": "W",
                "icon": "https://api.weather.gov/icons/land/day/rain,60/sct?size=medium",
                "shortForecast": "Chance Light Rain then Mostly Sunny",
                "detailedForecast": "A chance of rain before 11am. Mostly sunny, with a high near 48. West wind 9 to 15 mph. Chance of precipitation is 60%."
            },
            {
                "number": 7,
                "name": "Friday Night",
                "startTime": "2021-11-19T18:00:00-05:00",
                "endTime": "2021-11-20T06:00:00-05:00",
                "isDaytime": false,
                "temperature": 30,
                "temperatureUnit": "F",
                "temperatureTrend": null,
                "windSpeed": "6 to 10 mph",
                "windDirection": "NW",
                "icon": "https://api.weather.gov/icons/land/night/few?size=medium",
                "shortForecast": "Mostly Clear",
                "detailedForecast": "Mostly clear, with a low around 30. Northwest wind 6 to 10 mph."
            },
            {
                "number": 8,
                "name": "Saturday",
                "startTime": "2021-11-20T06:00:00-05:00",
                "endTime": "2021-11-20T18:00:00-05:00",
                "isDaytime": true,
                "temperature": 46,
                "temperatureUnit": "F",
                "temperatureTrend": null,
                "windSpeed": "6 mph",
                "windDirection": "W",
                "icon": "https://api.weather.gov/icons/land/day/sct?size=medium",
                "shortForecast": "Mostly Sunny",
                "detailedForecast": "Mostly sunny, with a high near 46. West wind around 6 mph."
            },
            {
                "number": 9,
                "name": "Saturday Night",
                "startTime": "2021-11-20T18:00:00-05:00",
                "endTime": "2021-11-21T06:00:00-05:00",
                "isDaytime": false,
                "temperature": 33,
                "temperatureUnit": "F",
                "temperatureTrend": null,
                "windSpeed": "5 mph",
                "windDirection": "S",
                "icon": "https://api.weather.gov/icons/land/night/bkn?size=medium",
                "shortForecast": "Mostly Cloudy",
                "detailedForecast": "Mostly cloudy, with a low around 33. South wind around 5 mph."
            },
            {
                "number": 10,
                "name": "Sunday",
                "startTime": "2021-11-21T06:00:00-05:00",
                "endTime": "2021-11-21T18:00:00-05:00",
                "isDaytime": true,
                "temperature": 52,
                "temperatureUnit": "F",
                "temperatureTrend": null,
                "windSpeed": "2 to 7 mph",
                "windDirection": "S",
                "icon": "https://api.weather.gov/icons/land/day/bkn/rain,30?size=medium",
                "shortForecast": "Mostly Cloudy then Chance Light Rain",
                "detailedForecast": "A chance of rain after noon. Mostly cloudy, with a high near 52. South wind 2 to 7 mph. Chance of precipitation is 30%."
            },
            {
                "number": 11,
                "name": "Sunday Night",
                "startTime": "2021-11-21T18:00:00-05:00",
                "endTime": "2021-11-22T06:00:00-05:00",
                "isDaytime": false,
                "temperature": 41,
                "temperatureUnit": "F",
                "temperatureTrend": null,
                "windSpeed": "3 mph",
                "windDirection": "S",
                "icon": "https://api.weather.gov/icons/land/night/rain,30/rain,40?size=medium",
                "shortForecast": "Chance Light Rain",
                "detailedForecast": "A chance of rain. Mostly cloudy, with a low around 41. South wind around 3 mph. Chance of precipitation is 40%."
            },
            {
                "number": 12,
                "name": "Monday",
                "startTime": "2021-11-22T06:00:00-05:00",
                "endTime": "2021-11-22T18:00:00-05:00",
                "isDaytime": true,
                "temperature": 55,
                "temperatureUnit": "F",
                "temperatureTrend": null,
                "windSpeed": "3 to 8 mph",
                "windDirection": "S",
                "icon": "https://api.weather.gov/icons/land/day/rain,50?size=medium",
                "shortForecast": "Chance Light Rain",
                "detailedForecast": "A chance of rain. Mostly cloudy, with a high near 55. South wind 3 to 8 mph. Chance of precipitation is 50%."
            },
            {
                "number": 13,
                "name": "Monday Night",
                "startTime": "2021-11-22T18:00:00-05:00",
                "endTime": "2021-11-23T06:00:00-05:00",
                "isDaytime": false,
                "temperature": 39,
                "temperatureUnit": "F",
                "temperatureTrend": null,
                "windSpeed": "6 to 9 mph",
                "windDirection": "S",
                "icon": "https://api.weather.gov/icons/land/night/rain,60?size=medium",
                "shortForecast": "Light Rain Likely",
                "detailedForecast": "Rain likely. Mostly cloudy, with a low around 39. South wind 6 to 9 mph. Chance of precipitation is 60%."
            },
            {
                "number": 14,
                "name": "Tuesday",
                "startTime": "2021-11-23T06:00:00-05:00",
                "endTime": "2021-11-23T18:00:00-05:00",
                "isDaytime": true,
                "temperature": 49,
                "temperatureUnit": "F",
                "temperatureTrend": null,
                "windSpeed": "9 to 13 mph",
                "windDirection": "S",
                "icon": "https://api.weather.gov/icons/land/day/rain,40/rain,30?size=medium",
                "shortForecast": "Chance Light Rain",
                "detailedForecast": "A chance of rain. Partly sunny, with a high near 49. South wind 9 to 13 mph, with gusts as high as 29 mph. Chance of precipitation is 40%."
            }
        ]
    }
}