[{"startTime":"2022-02-10T20:00:00-05:00","endTime":"2022-02-11T06:00:00-05:00","isDaytime":false,"temperature":31,"temperatureUnit":"F","temperatureTrend":null,"windSpeed":"3 to 9 mph","windDirection":"SW","icon":"https://api.weather.gov/icons/land/night/few?size=medium","shortForecast":"Mostly Clear","detailedForecast":"Mostly clear, with a low around 31. Southwest wind 3 to 9 mph.","updated":"2022-02-11T01:07:21+00:00"},{"startTime":"2022-02-11T06:00:00-05:00","endTime":"2022-02-11T18:00:00-05:00","isDaytime":true,"temperature":49,"temperatureUnit":"F","temperatureTrend":null,"windSpeed":"3 to 12 mph","windDirection":"SW","icon":"https://api.weather.gov/icons/land/day/few?size=medium","shortForecast":"Sunny","detailedForecast":"Sunny, with a high near 49. Southwest wind 3 to 12 mph, with gusts as high as 22 mph.","updated":"2022-02-11T01:07:21+00:00"},{"startTime":"2022-02-11T18:00:00-05:00","endTime":"2022-02-12T06:00:00-05:00","isDaytime":false,"temperature":39,"temperatureUnit":"F","temperatureTrend":null,"windSpeed":"8 to 12 mph","windDirection":"S","icon":"https://api.weather.gov/icons/land/night/bkn?size=medium","shortForecast":"Mostly Cloudy","detailedForecast":"Mostly cloudy, with a low around 39. South wind 8 to 12 mph, with gusts as high as 24 mph.","updated":"2022-02-11T01:07:21+00:00"},{"startTime":"2022-02-12T06:00:00-05:00","endTime":"2022-02-12T18:00:00-05:00","isDaytime":true,"temperature":60,"temperatureUnit":"F","temperatureTrend":null,"windSpeed":"9 to 13 mph","windDirection":"SW","icon":"https://api.weather.gov/icons/land/day/sct?size=medium","shortForecast":"Mostly Sunny","detailedForecast":"Mostly sunny, with a high near 60. Southwest wind 9 to 13 mph, with gusts as high as 24 mph.","updated":"2022-02-11T01:07:21+00:00"},{"startTime":"2022-02-12T18:00:00-05:00","endTime":"2022-02-13T06:00:00-05:00","isDaytime":false,"temperature":27,"temperatureUnit":"F","temperatureTrend":null,"windSpeed":"8 mph","windDirection":"NW","icon":"https://api.weather.gov/icons/land/night/snow,20/snow,40?size=medium","shortForecast":"Chance Light Snow","detailedForecast":"A slight chance of rain between 10pm and 11pm, then a chance of snow. Mostly cloudy, with a low around 27. Northwest wind around 8 mph. Chance of precipitation is 40%.","updated":"2022-02-11T01:07:21+00:00"},{"startTime":"2022-02-13T06:00:00-05:00","endTime":"2022-02-13T18:00:00-05:00","isDaytime":true,"temperature":31,"temperatureUnit":"F","temperatureTrend":null,"windSpeed":"8 mph","windDirection":"N","icon":"https://api.weather.gov/icons/land/day/snow,60?size=medium","shortForecast":"Light Snow Likely","detailedForecast":"Snow likely. Mostly cloudy, with a high near 31. North wind around 8 mph. Chance of precipitation is 60%. New snow accumulation of less than one inch possible.","updated":"2022-02-11T01:07:21+00:00"},{"startTime":"2022-02-13T18:00:00-05:00","endTime":"2022-02-14T06:00:00-05:00","isDaytime":false,"temperature":14,"temperatureUnit":"F","temperatureTrend":null,"windSpeed":"9 mph","windDirection":"N","icon":"https://api.weather.gov/icons/land/night/snow,30/snow?size=medium","shortForecast":"Chance Light Snow then Chance Snow Showers","detailedForecast":"A chance of snow before 7pm, then a chance of snow showers between 7pm and 4am. Mostly cloudy, with a low around 14. North wind around 9 mph. Chance of precipitation is 30%. Little or no snow accumulation expected.","updated":"2022-02-11T01:07:21+00:00"},{"startTime":"2022-02-14T06:00:00-05:00","endTime":"2022-02-14T18:00:00-05:00","isDaytime":true,"temperature":23,"temperatureUnit":"F","temperatureTrend":null,"windSpeed":"7 to 10 mph","windDirection":"NW","icon":"https://api.weather.gov/icons/land/day/sct?size=medium","shortForecast":"Mostly Sunny","detailedForecast":"Mostly sunny, with a high near 23. Northwest wind 7 to 10 mph.","updated":"2022-02-11T01:07:21+00:00"},{"startTime":"2022-02-14T18:00:00-05:00","endTime":"2022-02-15T06:00:00-05:00","isDaytime":false,"temperature":12,"temperatureUnit":"F","temperatureTrend":null,"windSpeed":"7 mph","windDirection":"NW","icon":"https://api.weather.gov/icons/land/night/sct?size=medium","shortForecast":"Partly Cloudy","detailedForecast":"Partly cloudy, with a low around 12. Northwest wind around 7 mph.","updated":"2022-02-11T01:07:21+00:00"},{"startTime":"2022-02-15T06:00:00-05:00","endTime":"2022-02-15T18:00:00-05:00","isDaytime":true,"temperature":32,"temperatureUnit":"F","temperatureTrend":null,"windSpeed":"6 to 9 mph","windDirection":"W","icon":"https://api.weather.gov/icons/land/day/sct?size=medium","shortForecast":"Mostly Sunny","detailedForecast":"Mostly sunny, with a high near 32. West wind 6 to 9 mph, with gusts as high as 21 mph.","updated":"2022-02-11T01:07:21+00:00"},{"startTime":"2022-02-15T18:00:00-05:00","endTime":"2022-02-16T06:00:00-05:00","isDaytime":false,"temperature":17,"temperatureUnit":"F","temperatureTrend":null,"windSpeed":"3 to 7 mph","windDirection":"NW","icon":"https://api.weather.gov/icons/land/night/sct?size=medium","shortForecast":"Partly Cloudy","detailedForecast":"Partly cloudy, with a low around 17. Northwest wind 3 to 7 mph.","updated":"2022-02-11T01:07:21+00:00"},{"startTime":"2022-02-16T06:00:00-05:00","endTime":"2022-02-16T18:00:00-05:00","isDaytime":true,"temperature":40,"temperatureUnit":"F","temperatureTrend":null,"windSpeed":"5 to 10 mph","windDirection":"SW","icon":"https://api.weather.gov/icons/land/day/sct?size=medium","shortForecast":"Mostly Sunny","detailedForecast":"Mostly sunny, with a high near 40. Southwest wind 5 to 10 mph, with gusts as high as 23 mph.","updated":"2022-02-11T01:07:21+00:00"},{"startTime":"2022-02-16T18:00:00-05:00","endTime":"2022-02-17T06:00:00-05:00","isDaytime":false,"temperature":33,"temperatureUnit":"F","temperatureTrend":null,"windSpeed":"10 mph","windDirection":"SW","icon":"https://api.weather.gov/icons/land/night/bkn?size=medium","shortForecast":"Mostly Cloudy","detailedForecast":"Mostly cloudy, with a low around 33. Southwest wind around 10 mph, with gusts as high as 22 mph.","updated":"2022-02-11T01:07:21+00:00"},{"startTime":"2022-02-17T06:00:00-05:00","endTime":"2022-02-17T18:00:00-05:00","isDaytime":true,"temperature":55,"temperatureUnit":"F","temperatureTrend":null,"windSpeed":"12 to 15 mph","windDirection":"SW","icon":"https://api.weather.gov/icons/land/day/rain_showers,30/rain_showers,40?size=medium","shortForecast":"Chance Rain Showers","detailedForecast":"A chance of rain showers after 8am. Mostly cloudy, with a high near 55. Southwest wind 12 to 15 mph, with gusts as high as 26 mph. Chance of precipitation is 40%.","updated":"2022-02-11T01:07:21+00:00"}]